groupit/__init__.py
groupit/cli/__init__.py
groupit/cli/commands/__init__.py
groupit/cli/commands/analyze.py
groupit/cli/commands/commit.py
groupit/cli/commands/status.py
groupit/cli/commands/validate.py
groupit/cli/parser.py
groupit/config/__init__.py
groupit/config/logging_config.py
groupit/config/settings.py
groupit/core/__init__.py
groupit/core/agent.py
groupit/core/clustering.py
groupit/core/git_operations.py
groupit/core/models/__init__.py
groupit/core/models/change_block.py
groupit/core/models/commit_group.py
groupit/core/models/grouping_result.py
groupit/core/parsing.py
groupit/core/pipeline.py
groupit/language_support.py
groupit/llm/__init__.py
groupit/llm/base.py
groupit/llm/factory.py
groupit/llm/providers/__init__.py
groupit/llm/providers/gemini_provider.py
groupit/llm/providers/ollama_provider.py
groupit/llm/providers/openai_provider.py
groupit/llm/providers/registry.py
groupit/main.py
groupit/processors/__init__.py
groupit/processors/base.py
groupit/processors/message_generator.py
groupit/processors/primary_grouping.py
groupit/processors/semantic_grouper.py
groupit/processors/summary_generator.py
groupit-0.1.2.dist-info/WHEEL
groupit-0.1.2.dist-info/entry_points.txt
groupit-0.1.2.dist-info/METADATA
groupit-0.1.2.dist-info/RECORD
