Metadata-Version: 2.3
Name: groupit
Version: 0.1.2
Summary: AI-powered Git commit grouping tool for semantic code organization
Keywords: git,commit,ai,semantic,grouping,agent
Author: jarry3369
Author-email: jarry3369 <jarry3369@gmail.com>
Requires-Dist: gitpython>=3.1.45
Requires-Dist: google-genai>=1.4.0
Requires-Dist: networkx>=3.5
Requires-Dist: numpy>=2.3.2
Requires-Dist: ollama>=0.3.1
Requires-Dist: openai>=1.104.2
Requires-Dist: rich>=14.1.0
Requires-Dist: scikit-learn>=1.7.1
Requires-Dist: sentence-transformers>=5.1.0
Requires-Dist: tree-sitter>=0.25.1
Requires-Dist: unidiff>=0.7.5
Requires-Python: >=3.12
Project-URL: Documentation, https://github.com/jarry3369/groupit/blob/main/README.md
Project-URL: Issues, https://github.com/jarry3369/groupit/issues
Project-URL: Repository, https://github.com/jarry3369/groupit
